{"packages":{"wpackagist-plugin\/123devis-affiliation":{"1.0.4":{"name":"wpackagist-plugin\/123devis-affiliation","version":"1.0.4","version_normalized":"1.0.4.0","uid":145,"dist":{"type":"zip","url":"http:\/\/downloads.wordpress.org\/plugin\/123devis-affiliation.1.0.4.zip"},"source":{"type":"svn","url":"http:\/\/plugins.svn.wordpress.org\/123devis-affiliation\/","reference":"tags\/1.0.4"},"homepage":"https:\/\/wordpress.org\/plugins\/123devis-affiliation\/","require":{"composer\/installers":"~1.0"},"type":"wordpress-plugin"},"dev-trunk":{"name":"wpackagist-plugin\/123devis-affiliation","version":"dev-trunk","version_normalized":"9999999-dev","uid":146,"time":"2014-03-10 11:19:07","dist":{"type":"zip","url":"http:\/\/downloads.wordpress.org\/plugin\/123devis-affiliation.zip"},"source":{"type":"svn","url":"http:\/\/plugins.svn.wordpress.org\/123devis-affiliation\/","reference":"trunk"},"homepage":"https:\/\/wordpress.org\/plugins\/123devis-affiliation\/","require":{"composer\/installers":"~1.0"},"type":"wordpress-plugin"},"1.0.3":{"name":"wpackagist-plugin\/123devis-affiliation","version":"1.0.3","version_normalized":"1.0.3.0","uid":147,"dist":{"type":"zip","url":"http:\/\/downloads.wordpress.org\/plugin\/123devis-affiliation.1.0.3.zip"},"source":{"type":"svn","url":"http:\/\/plugins.svn.wordpress.org\/123devis-affiliation\/","reference":"tags\/1.0.3"},"homepage":"https:\/\/wordpress.org\/plugins\/123devis-affiliation\/","require":{"composer\/installers":"~1.0"},"type":"wordpress-plugin"},"1.0.2":{"name":"wpackagist-plugin\/123devis-affiliation","version":"1.0.2","version_normalized":"1.0.2.0","uid":148,"dist":{"type":"zip","url":"http:\/\/downloads.wordpress.org\/plugin\/123devis-affiliation.1.0.2.zip"},"source":{"type":"svn","url":"http:\/\/plugins.svn.wordpress.org\/123devis-affiliation\/","reference":"tags\/1.0.2"},"homepage":"https:\/\/wordpress.org\/plugins\/123devis-affiliation\/","require":{"composer\/installers":"~1.0"},"type":"wordpress-plugin"},"1.0.1":{"name":"wpackagist-plugin\/123devis-affiliation","version":"1.0.1","version_normalized":"1.0.1.0","uid":149,"dist":{"type":"zip","url":"http:\/\/downloads.wordpress.org\/plugin\/123devis-affiliation.1.0.1.zip"},"source":{"type":"svn","url":"http:\/\/plugins.svn.wordpress.org\/123devis-affiliation\/","reference":"tags\/1.0.1"},"homepage":"https:\/\/wordpress.org\/plugins\/123devis-affiliation\/","require":{"composer\/installers":"~1.0"},"type":"wordpress-plugin"},"1.0.0":{"name":"wpackagist-plugin\/123devis-affiliation","version":"1.0.0","version_normalized":"1.0.0.0","uid":150,"dist":{"type":"zip","url":"http:\/\/downloads.wordpress.org\/plugin\/123devis-affiliation.1.0.0.zip"},"source":{"type":"svn","url":"http:\/\/plugins.svn.wordpress.org\/123devis-affiliation\/","reference":"tags\/1.0.0"},"homepage":"https:\/\/wordpress.org\/plugins\/123devis-affiliation\/","require":{"composer\/installers":"~1.0"},"type":"wordpress-plugin"}}}}