{"packages":{"wpackagist-plugin\/3d-viewer-configurator":{"1.7.3":{"name":"wpackagist-plugin\/3d-viewer-configurator","version":"1.7.3","version_normalized":"1.7.3.0","uid":478,"dist":{"type":"zip","url":"http:\/\/downloads.wordpress.org\/plugin\/3d-viewer-configurator.1.7.3.zip"},"source":{"type":"svn","url":"http:\/\/plugins.svn.wordpress.org\/3d-viewer-configurator\/","reference":"tags\/1.8.1"},"homepage":"https:\/\/wordpress.org\/plugins\/3d-viewer-configurator\/","require":{"composer\/installers":"~1.0"},"type":"wordpress-plugin"},"dev-trunk":{"name":"wpackagist-plugin\/3d-viewer-configurator","version":"dev-trunk","version_normalized":"9999999-dev","uid":479,"time":"2014-10-11 09:48:55","dist":{"type":"zip","url":"http:\/\/downloads.wordpress.org\/plugin\/3d-viewer-configurator.zip"},"source":{"type":"svn","url":"http:\/\/plugins.svn.wordpress.org\/3d-viewer-configurator\/","reference":"trunk"},"homepage":"https:\/\/wordpress.org\/plugins\/3d-viewer-configurator\/","require":{"composer\/installers":"~1.0"},"type":"wordpress-plugin"},"1.8":{"name":"wpackagist-plugin\/3d-viewer-configurator","version":"1.8","version_normalized":"1.8.0.0","uid":480,"dist":{"type":"zip","url":"http:\/\/downloads.wordpress.org\/plugin\/3d-viewer-configurator.1.8.zip"},"source":{"type":"svn","url":"http:\/\/plugins.svn.wordpress.org\/3d-viewer-configurator\/","reference":"tags\/1.8"},"homepage":"https:\/\/wordpress.org\/plugins\/3d-viewer-configurator\/","require":{"composer\/installers":"~1.0"},"type":"wordpress-plugin"},"1.6":{"name":"wpackagist-plugin\/3d-viewer-configurator","version":"1.6","version_normalized":"1.6.0.0","uid":481,"dist":{"type":"zip","url":"http:\/\/downloads.wordpress.org\/plugin\/3d-viewer-configurator.1.6.zip"},"source":{"type":"svn","url":"http:\/\/plugins.svn.wordpress.org\/3d-viewer-configurator\/","reference":"tags\/1.6"},"homepage":"https:\/\/wordpress.org\/plugins\/3d-viewer-configurator\/","require":{"composer\/installers":"~1.0"},"type":"wordpress-plugin"},"1.5.2":{"name":"wpackagist-plugin\/3d-viewer-configurator","version":"1.5.2","version_normalized":"1.5.2.0","uid":482,"dist":{"type":"zip","url":"http:\/\/downloads.wordpress.org\/plugin\/3d-viewer-configurator.1.5.2.zip"},"source":{"type":"svn","url":"http:\/\/plugins.svn.wordpress.org\/3d-viewer-configurator\/","reference":"tags\/1.5.2"},"homepage":"https:\/\/wordpress.org\/plugins\/3d-viewer-configurator\/","require":{"composer\/installers":"~1.0"},"type":"wordpress-plugin"},"1.5.1":{"name":"wpackagist-plugin\/3d-viewer-configurator","version":"1.5.1","version_normalized":"1.5.1.0","uid":483,"dist":{"type":"zip","url":"http:\/\/downloads.wordpress.org\/plugin\/3d-viewer-configurator.1.5.1.zip"},"source":{"type":"svn","url":"http:\/\/plugins.svn.wordpress.org\/3d-viewer-configurator\/","reference":"tags\/1.5.1"},"homepage":"https:\/\/wordpress.org\/plugins\/3d-viewer-configurator\/","require":{"composer\/installers":"~1.0"},"type":"wordpress-plugin"},"1.5":{"name":"wpackagist-plugin\/3d-viewer-configurator","version":"1.5","version_normalized":"1.5.0.0","uid":484,"dist":{"type":"zip","url":"http:\/\/downloads.wordpress.org\/plugin\/3d-viewer-configurator.1.5.zip"},"source":{"type":"svn","url":"http:\/\/plugins.svn.wordpress.org\/3d-viewer-configurator\/","reference":"tags\/1.5"},"homepage":"https:\/\/wordpress.org\/plugins\/3d-viewer-configurator\/","require":{"composer\/installers":"~1.0"},"type":"wordpress-plugin"}}}}