{"packages":{"wpackagist-plugin\/a3-lazy-load":{"1.0.0":{"name":"wpackagist-plugin\/a3-lazy-load","version":"1.0.0","version_normalized":"1.0.0.0","uid":890,"dist":{"type":"zip","url":"http:\/\/downloads.wordpress.org\/plugin\/a3-lazy-load.zip"},"source":{"type":"svn","url":"http:\/\/plugins.svn.wordpress.org\/a3-lazy-load\/","reference":"trunk"},"homepage":"https:\/\/wordpress.org\/plugins\/a3-lazy-load\/","require":{"composer\/installers":"~1.0"},"type":"wordpress-plugin"},"dev-trunk":{"name":"wpackagist-plugin\/a3-lazy-load","version":"dev-trunk","version_normalized":"9999999-dev","uid":891,"time":"2014-12-19 22:39:31","dist":{"type":"zip","url":"http:\/\/downloads.wordpress.org\/plugin\/a3-lazy-load.zip"},"source":{"type":"svn","url":"http:\/\/plugins.svn.wordpress.org\/a3-lazy-load\/","reference":"trunk"},"homepage":"https:\/\/wordpress.org\/plugins\/a3-lazy-load\/","require":{"composer\/installers":"~1.0"},"type":"wordpress-plugin"}}}}