{"packages":{"wpackagist-plugin\/add-google-plusone":{"0.4":{"name":"wpackagist-plugin\/add-google-plusone","version":"0.4","version_normalized":"0.4.0.0","uid":2305,"dist":{"type":"zip","url":"http:\/\/downloads.wordpress.org\/plugin\/add-google-plusone.0.4.zip"},"source":{"type":"svn","url":"http:\/\/plugins.svn.wordpress.org\/add-google-plusone\/","reference":"tags\/0.4"},"homepage":"https:\/\/wordpress.org\/plugins\/add-google-plusone\/","require":{"composer\/installers":"~1.0"},"type":"wordpress-plugin"},"dev-trunk":{"name":"wpackagist-plugin\/add-google-plusone","version":"dev-trunk","version_normalized":"9999999-dev","uid":2306,"time":"2011-10-05 23:57:11","dist":{"type":"zip","url":"http:\/\/downloads.wordpress.org\/plugin\/add-google-plusone.zip"},"source":{"type":"svn","url":"http:\/\/plugins.svn.wordpress.org\/add-google-plusone\/","reference":"trunk"},"homepage":"https:\/\/wordpress.org\/plugins\/add-google-plusone\/","require":{"composer\/installers":"~1.0"},"type":"wordpress-plugin"},"0.3":{"name":"wpackagist-plugin\/add-google-plusone","version":"0.3","version_normalized":"0.3.0.0","uid":2307,"dist":{"type":"zip","url":"http:\/\/downloads.wordpress.org\/plugin\/add-google-plusone.0.3.zip"},"source":{"type":"svn","url":"http:\/\/plugins.svn.wordpress.org\/add-google-plusone\/","reference":"tags\/0.3"},"homepage":"https:\/\/wordpress.org\/plugins\/add-google-plusone\/","require":{"composer\/installers":"~1.0"},"type":"wordpress-plugin"},"0.2":{"name":"wpackagist-plugin\/add-google-plusone","version":"0.2","version_normalized":"0.2.0.0","uid":2308,"dist":{"type":"zip","url":"http:\/\/downloads.wordpress.org\/plugin\/add-google-plusone.0.2.zip"},"source":{"type":"svn","url":"http:\/\/plugins.svn.wordpress.org\/add-google-plusone\/","reference":"tags\/0.2"},"homepage":"https:\/\/wordpress.org\/plugins\/add-google-plusone\/","require":{"composer\/installers":"~1.0"},"type":"wordpress-plugin"}}}}