{"packages":{"wpackagist-plugin\/addynamo-plugin":{"1":{"name":"wpackagist-plugin\/addynamo-plugin","version":1,"version_normalized":"1.0.0.0","uid":3075,"dist":{"type":"zip","url":"http:\/\/downloads.wordpress.org\/plugin\/addynamo-plugin.1.zip"},"source":{"type":"svn","url":"http:\/\/plugins.svn.wordpress.org\/addynamo-plugin\/","reference":"tags\/1.0.0.0"},"homepage":"https:\/\/wordpress.org\/plugins\/addynamo-plugin\/","require":{"composer\/installers":"~1.0"},"type":"wordpress-plugin"},"dev-trunk":{"name":"wpackagist-plugin\/addynamo-plugin","version":"dev-trunk","version_normalized":"9999999-dev","uid":3076,"time":"2008-11-26 07:12:20","dist":{"type":"zip","url":"http:\/\/downloads.wordpress.org\/plugin\/addynamo-plugin.zip"},"source":{"type":"svn","url":"http:\/\/plugins.svn.wordpress.org\/addynamo-plugin\/","reference":"trunk"},"homepage":"https:\/\/wordpress.org\/plugins\/addynamo-plugin\/","require":{"composer\/installers":"~1.0"},"type":"wordpress-plugin"}}}}