{"packages":{"wpackagist-plugin\/agregador-de-links-pastando":{"1.0":{"name":"wpackagist-plugin\/agregador-de-links-pastando","version":"1.0","version_normalized":"1.0.0.0","uid":6390,"dist":{"type":"zip","url":"http:\/\/downloads.wordpress.org\/plugin\/agregador-de-links-pastando.zip"},"source":{"type":"svn","url":"http:\/\/plugins.svn.wordpress.org\/agregador-de-links-pastando\/","reference":"trunk"},"homepage":"https:\/\/wordpress.org\/plugins\/agregador-de-links-pastando\/","require":{"composer\/installers":"~1.0"},"type":"wordpress-plugin"},"dev-trunk":{"name":"wpackagist-plugin\/agregador-de-links-pastando","version":"dev-trunk","version_normalized":"9999999-dev","uid":6391,"time":"2011-02-28 08:39:55","dist":{"type":"zip","url":"http:\/\/downloads.wordpress.org\/plugin\/agregador-de-links-pastando.zip"},"source":{"type":"svn","url":"http:\/\/plugins.svn.wordpress.org\/agregador-de-links-pastando\/","reference":"trunk"},"homepage":"https:\/\/wordpress.org\/plugins\/agregador-de-links-pastando\/","require":{"composer\/installers":"~1.0"},"type":"wordpress-plugin"}}}}