{"packages":{"wpackagist-plugin\/allegrato":{"0.0.1":{"name":"wpackagist-plugin\/allegrato","version":"0.0.1","version_normalized":"0.0.1.0","uid":7896,"dist":{"type":"zip","url":"http:\/\/downloads.wordpress.org\/plugin\/allegrato.zip"},"source":{"type":"svn","url":"http:\/\/plugins.svn.wordpress.org\/allegrato\/","reference":"trunk"},"homepage":"https:\/\/wordpress.org\/plugins\/allegrato\/","require":{"composer\/installers":"~1.0"},"type":"wordpress-plugin"},"dev-trunk":{"name":"wpackagist-plugin\/allegrato","version":"dev-trunk","version_normalized":"9999999-dev","uid":7897,"time":"2011-02-26 04:28:34","dist":{"type":"zip","url":"http:\/\/downloads.wordpress.org\/plugin\/allegrato.zip"},"source":{"type":"svn","url":"http:\/\/plugins.svn.wordpress.org\/allegrato\/","reference":"trunk"},"homepage":"https:\/\/wordpress.org\/plugins\/allegrato\/","require":{"composer\/installers":"~1.0"},"type":"wordpress-plugin"}}}}